purplship/mappers/ups_ground/__init__.py
purplship/mappers/ups_ground/mapper.py
purplship/mappers/ups_ground/proxy.py
purplship/mappers/ups_ground/settings.py
purplship/providers/ups_ground/__init__.py
purplship/providers/ups_ground/error.py
purplship/providers/ups_ground/pickup/__init__.py
purplship/providers/ups_ground/pickup/cancel.py
purplship/providers/ups_ground/pickup/create.py
purplship/providers/ups_ground/pickup/update.py
purplship/providers/ups_ground/rate.py
purplship/providers/ups_ground/shipment/__init__.py
purplship/providers/ups_ground/shipment/create.py
purplship/providers/ups_ground/tracking.py
purplship/providers/ups_ground/units.py
purplship/providers/ups_ground/utils.py
purplship.ups_ground-2021.10.1.dist-info/WHEEL
purplship.ups_ground-2021.10.1.dist-info/METADATA
purplship.ups_ground-2021.10.1.dist-info/RECORD
